spinasm_lsp/__init__.py
spinasm_lsp/parser.py
spinasm_lsp/server.py
spinasm_lsp/tokens.py
spinasm_lsp/docs/__init__.py
spinasm_lsp/docs/assemblers.py
spinasm_lsp/docs/instructions.py
spinasm_lsp/docs/markdown.py
spinasm_lsp-0.1.2.dist-info/METADATA
spinasm_lsp-0.1.2.dist-info/WHEEL
spinasm_lsp-0.1.2.dist-info/entry_points.txt
spinasm_lsp-0.1.2.dist-info/licenses/LICENSE
spinasm_lsp-0.1.2.dist-info/RECORD
