Metadata-Version: 2.3
Name: spinasm-lsp
Version: 0.1.2
Summary: A Language Server Protocol implementation for SPINAsm
Project-URL: Homepage, https://github.com/aazuspan/spinasm-lsp
Author: Aaron Zuspan
License: MIT License
License-File: LICENSE
Keywords: lsp,spinasm
Classifier: License :: OSI Approved :: MIT License
Classifier: Programming Language :: Python :: 3.8
Classifier: Programming Language :: Python :: 3.9
Classifier: Programming Language :: Python :: 3.10
Classifier: Programming Language :: Python :: 3.11
Classifier: Programming Language :: Python :: 3.12
Classifier: Typing :: Typed
Requires-Python: >=3.8
Requires-Dist: asfv1==1.2.7
Requires-Dist: lsprotocol
Requires-Dist: pygls
